magic5/__init__.py
magic5-0.2.0.dist-info/licenses/LICENSE
magic5-0.2.0.dist-info/METADATA
magic5-0.2.0.dist-info/WHEEL
magic5-0.2.0.dist-info/top_level.txt
magic5-0.2.0.dist-info/RECORD
